smskillsdk/__init__.py
smskillsdk/models/__init__.py
smskillsdk/models/api.py
smskillsdk/models/api_async.py
smskillsdk/models/common.py
smskillsdk/utils/__init__.py
smskillsdk/utils/memory.py
smskillsdk/utils/memory_values.py
smskillsdk-1.0.0.dist-info/LICENSE
smskillsdk-1.0.0.dist-info/METADATA
smskillsdk-1.0.0.dist-info/WHEEL
smskillsdk-1.0.0.dist-info/top_level.txt
smskillsdk-1.0.0.dist-info/RECORD
