Metadata-Version: 2.1
Name: smskillsdk
Version: 1.0.0
Summary: A Python package to assist with developing services conforming to the Soul Machines Skill REST API.
Home-page: https://docs.soulmachines.com
Author: Soul Machines Ltd
License: Apache 2.0
Project-URL: Documentation, https://docs.soulmachines.com
Classifier: Development Status :: 2 - Pre-Alpha
Classifier: Intended Audience :: Developers
Classifier: Topic :: Software Development :: Libraries
Classifier: License :: OSI Approved :: Apache Software License
Classifier: Programming Language :: Python :: 3.8
Classifier: Programming Language :: Python :: 3.9
Classifier: Programming Language :: Python :: 3.10
Requires-Python: >=3.8
License-File: LICENSE
Requires-Dist: pydantic>=1.8.2
